{
  "ep": 349,
  "gp": 401,
  "log": [
    {
      "ep": 0,
      "gp": 50,
      "description": null,
      "timestamp": 1633991197
    },
    {
      "ep": 17,
      "gp": 50,
      "description": "Add EP 17 (Hazard pay)",
      "timestamp": 1635473877
    },
    {
      "ep": 34,
      "gp": 50,
      "description": "Add EP 17 (Hazard pay)",
      "timestamp": 1635476807
    },
    {
      "ep": 51,
      "gp": 50,
      "description": "Add EP 17 (Hazard pay)",
      "timestamp": 1635479195
    },
    {
      "ep": 40,
      "gp": 50,
      "description": "20% weekly EP decay",
      "timestamp": 1635900435
    },
    {
      "ep": 57,
      "gp": 50,
      "description": "Add EP 17 (Killed Al'ar)",
      "timestamp": 1635904586
    },
    {
      "ep": 74,
      "gp": 50,
      "description": "Add EP 17 (Killed Void Reaver)",
      "timestamp": 1635908036
    },
    {
      "ep": 91,
      "gp": 50,
      "description": "Add EP 17 (Killed High Astromancer Solarian)",
      "timestamp": 1635910261
    },
    {
      "ep": 108,
      "gp": 50,
      "description": "Add EP 17 (Hazard pay)",
      "timestamp": 1636078225
    },
    {
      "ep": 125,
      "gp": 50,
      "description": "Add EP 17 (Hazard pay)",
      "timestamp": 1636081545
    },
    {
      "ep": 142,
      "gp": 50,
      "description": "Add EP 17 (Killed Leotheras the Blind)",
      "timestamp": 1636513750
    },
    {
      "ep": 159,
      "gp": 50,
      "description": "Add EP 17 (Killed Fathom-Lord Karathress)",
      "timestamp": 1636515191
    },
    {
      "ep": 176,
      "gp": 50,
      "description": "Add EP 17 (Killed Morogrim Tidewalker)",
      "timestamp": 1636516541
    },
    {
      "ep": 193,
      "gp": 50,
      "description": "Add EP 17 (Killed The Lurker Below)",
      "timestamp": 1636518028
    },
    {
      "ep": 154,
      "gp": 50,
      "description": "20% weekly EP decay",
      "timestamp": 1636521978
    },
    {
      "ep": 171,
      "gp": 50,
      "description": "Add EP 17 (Killed Al'ar)",
      "timestamp": 1636684569
    },
    {
      "ep": 188,
      "gp": 50,
      "description": "Add EP 17 (Killed Void Reaver)",
      "timestamp": 1636686222
    },
    {
      "ep": 188,
      "gp": 175,
      "description": "Add GP 125 (Full Price)\n[Pauldrons of the Vanquished Hero]",
      "timestamp": 1636686325
    },
    {
      "ep": 205,
      "gp": 175,
      "description": "Add EP 17 (Killed High Astromancer Solarian)",
      "timestamp": 1636687891
    },
    {
      "ep": 164,
      "gp": 175,
      "description": "20% weekly EP decay",
      "timestamp": 1637112998
    },
    {
      "ep": 164,
      "gp": 143,
      "description": "25% weekly GP decay",
      "timestamp": 1637113010
    },
    {
      "ep": 181,
      "gp": 143,
      "description": "Add EP 17 (Killed Al'ar)",
      "timestamp": 1637117092
    },
    {
      "ep": 198,
      "gp": 143,
      "description": "Add EP 17 (Killed Void Reaver)",
      "timestamp": 1637119491
    },
    {
      "ep": 198,
      "gp": 216,
      "description": "Add GP 73 (Full Price)\n[Bands of the Celestial Archer]",
      "timestamp": 1637120459
    },
    {
      "ep": 215,
      "gp": 216,
      "description": "Add EP 17 (Killed High Astromancer Solarian)",
      "timestamp": 1637122392
    },
    {
      "ep": 283,
      "gp": 219,
      "description": null,
      "timestamp": 1637693491
    },
    {
      "ep": 226,
      "gp": 219,
      "description": "20% weekly EP decay",
      "timestamp": 1637693516
    },
    {
      "ep": 226,
      "gp": 176,
      "description": null,
      "timestamp": 1637693562
    },
    {
      "ep": 241,
      "gp": 176,
      "description": "Add EP 15 (Killed High King Maulgar)",
      "timestamp": 1637721726
    },
    {
      "ep": 226,
      "gp": 176,
      "description": null,
      "timestamp": 1637721812
    },
    {
      "ep": 180,
      "gp": 176,
      "description": "20% weekly EP decay",
      "timestamp": 1638321741
    },
    {
      "ep": 180,
      "gp": 144,
      "description": "25% weekly GP decay",
      "timestamp": 1638321760
    },
    {
      "ep": 197,
      "gp": 144,
      "description": "Add EP 17 (Killed Void Reaver)",
      "timestamp": 1638327932
    },
    {
      "ep": 157,
      "gp": 144,
      "description": "20% weekly EP decay",
      "timestamp": 1638907821
    },
    {
      "ep": 157,
      "gp": 120,
      "description": "25% weekly GP decay",
      "timestamp": 1638907826
    },
    {
      "ep": 174,
      "gp": 120,
      "description": "Add EP 17 (Killed The Lurker Below)",
      "timestamp": 1638933932
    },
    {
      "ep": 191,
      "gp": 120,
      "description": "Add EP 17 (Killed Leotheras the Blind)",
      "timestamp": 1638937172
    },
    {
      "ep": 208,
      "gp": 120,
      "description": "Add EP 17 (Killed Fathom-Lord Karathress)",
      "timestamp": 1638939842
    },
    {
      "ep": 208,
      "gp": 287,
      "description": "Add GP 167 (Full Price)\n[Leggings of the Vanquished Hero]",
      "timestamp": 1638940060
    },
    {
      "ep": 166,
      "gp": 287,
      "description": "20% weekly EP decay",
      "timestamp": 1639532012
    },
    {
      "ep": 166,
      "gp": 227,
      "description": "25% weekly GP decay",
      "timestamp": 1639532021
    },
    {
      "ep": 183,
      "gp": 227,
      "description": "Add EP 17 (Killed Al'ar)",
      "timestamp": 1639535968
    },
    {
      "ep": 183,
      "gp": 484,
      "description": "Add GP +257 (\"Cool\" \"axe\")",
      "timestamp": 1639536959
    },
    {
      "ep": 200,
      "gp": 484,
      "description": "Add EP 17 (Killed Void Reaver)",
      "timestamp": 1639537732
    },
    {
      "ep": 217,
      "gp": 484,
      "description": "Add EP 17 (Killed The Lurker Below)",
      "timestamp": 1639709056
    },
    {
      "ep": 237,
      "gp": 484,
      "description": "Add EP 20 (Killed Lady Vashj)",
      "timestamp": 1639710171
    },
    {
      "ep": 254,
      "gp": 484,
      "description": "Add EP 17 (Killed Leotheras the Blind)",
      "timestamp": 1639712104
    },
    {
      "ep": 271,
      "gp": 484,
      "description": "Add EP 17 (Killed Fathom-Lord Karathress)",
      "timestamp": 1639714047
    },
    {
      "ep": 288,
      "gp": 484,
      "description": "Add EP 17 (Killed Morogrim Tidewalker)",
      "timestamp": 1639715132
    },
    {
      "ep": 230,
      "gp": 484,
      "description": "20% weekly EP decay",
      "timestamp": 1640116869
    },
    {
      "ep": 230,
      "gp": 375,
      "description": "25% weekly GP decay",
      "timestamp": 1640116877
    },
    {
      "ep": 247,
      "gp": 375,
      "description": "Add EP 17 (Killed Al'ar)",
      "timestamp": 1640140307
    },
    {
      "ep": 197,
      "gp": 375,
      "description": "20% weekly EP decay",
      "timestamp": 1640739794
    },
    {
      "ep": 197,
      "gp": 293,
      "description": "25% weekly GP decay",
      "timestamp": 1640739804
    },
    {
      "ep": 214,
      "gp": 293,
      "description": "Add EP 17 (Killed Al'ar)",
      "timestamp": 1640745688
    },
    {
      "ep": 231,
      "gp": 293,
      "description": "Add EP 17 (Killed Void Reaver)",
      "timestamp": 1640747515
    },
    {
      "ep": 248,
      "gp": 293,
      "description": "Add EP 17 (Killed High Astromancer Solarian)",
      "timestamp": 1640749885
    },
    {
      "ep": 265,
      "gp": 293,
      "description": "Add EP 17 (Killed The Lurker Below)",
      "timestamp": 1640919182
    },
    {
      "ep": 285,
      "gp": 293,
      "description": "Add EP 20 (Killed Lady Vashj)",
      "timestamp": 1640923521
    },
    {
      "ep": 285,
      "gp": 436,
      "description": "Add GP 143 (Full Price)\n[Cobra-Lash Boots]",
      "timestamp": 1640923907
    },
    {
      "ep": 302,
      "gp": 436,
      "description": "Add EP 17 (Killed Leotheras the Blind)",
      "timestamp": 1640925441
    },
    {
      "ep": 319,
      "gp": 436,
      "description": "Add EP 17 (Killed Fathom-Lord Karathress)",
      "timestamp": 1640926865
    },
    {
      "ep": 255,
      "gp": 436,
      "description": "20% weekly EP decay",
      "timestamp": 1641344903
    },
    {
      "ep": 255,
      "gp": 339,
      "description": "25% weekly GP decay",
      "timestamp": 1641344916
    },
    {
      "ep": 326,
      "gp": 506,
      "description": null,
      "timestamp": 1641534718
    },
    {
      "ep": 260,
      "gp": 506,
      "description": "20% weekly EP decay",
      "timestamp": 1641932378
    },
    {
      "ep": 260,
      "gp": 392,
      "description": "25% weekly GP decay",
      "timestamp": 1641932382
    },
    {
      "ep": 277,
      "gp": 392,
      "description": "Add EP 17 (Killed The Lurker Below)",
      "timestamp": 1642128258
    },
    {
      "ep": 297,
      "gp": 392,
      "description": "Add EP 20 (Killed Lady Vashj)",
      "timestamp": 1642129633
    },
    {
      "ep": 314,
      "gp": 392,
      "description": "Add EP 17 (Killed Morogrim Tidewalker)",
      "timestamp": 1642131980
    },
    {
      "ep": 331,
      "gp": 392,
      "description": "Add EP 17 (Killed Fathom-Lord Karathress)",
      "timestamp": 1642132976
    },
    {
      "ep": 348,
      "gp": 392,
      "description": "Add EP 17 (Killed Leotheras the Blind)",
      "timestamp": 1642134416
    },
    {
      "ep": 278,
      "gp": 392,
      "description": "20% weekly EP decay",
      "timestamp": 1642536618
    },
    {
      "ep": 278,
      "gp": 306,
      "description": "25% weekly GP decay",
      "timestamp": 1642536626
    },
    {
      "ep": 295,
      "gp": 306,
      "description": "Add EP 17 (Killed Al'ar)",
      "timestamp": 1642732016
    },
    {
      "ep": 312,
      "gp": 306,
      "description": "Add EP 17 (Killed Void Reaver)",
      "timestamp": 1642733767
    },
    {
      "ep": 329,
      "gp": 306,
      "description": "Add EP 17 (Killed High Astromancer Solarian)",
      "timestamp": 1642735998
    },
    {
      "ep": 349,
      "gp": 306,
      "description": "Add EP 20 (Killed Kael'thas Sunstrider)",
      "timestamp": 1642736963
    },
    {
      "ep": 349,
      "gp": 401,
      "description": "Add GP 95 (Minor (50%))\n[Leggings of Murderous Intent]",
      "timestamp": 1642737195
    }
  ]
}